kzleet/Easy.py
kzleet/Hard.py
kzleet/Medium.py
kzleet/Solution.py
kzleet/__init__.py
kzleet-2025.8.7.0.dist-info/METADATA
kzleet-2025.8.7.0.dist-info/WHEEL
kzleet-2025.8.7.0.dist-info/top_level.txt
kzleet-2025.8.7.0.dist-info/RECORD
