Metadata-Version: 2.4
Name: kzleet
Version: 2025.8.7.0
Summary: a library with frequently updated LeetCode solutions created by the community
Author: Kevin Zhu
Author-email: kzhu2099@gmail.com
Maintainer: Kevin Zhu
Maintainer-email: kzhu2099@gmail.com
License: MIT License
Project-URL: Homepage, https://github.com/kzhu2099/KZ-leet
Project-URL: Issues, https://github.com/kzhu2099/KZ-leet/issues
Classifier: Development Status :: 7 - Inactive
Classifier: Intended Audience :: Developers
Classifier: Intended Audience :: End Users/Desktop
Classifier: License :: OSI Approved :: MIT License
Classifier: Natural Language :: English
Classifier: Operating System :: OS Independent
Classifier: Programming Language :: Python :: 3
Requires-Python: >=3.9
